{
            "instance_id": "EZCRJN",
            "problem_statement": "Develop a Python module to define, calculate, and manage features that monitor customer behavior and engagement patterns on a large-scale e-commerce platform. The goal is to provide actionable and measurable features that help detect early signs of customers losing interest. This will enable targeted marketing, retention strategies, and personalized campaigns. The module should focus strictly on defining and calculating customer activity features, without implementing any predictive models or machine learning algorithms.",
            "base_commit": "repository_before/",
            "test_patch": "tests/",
            "github_url": "https://github.com/ep-eaglepoint-ai/bd_datasets_003/tree/main/ezcrjn-customer-activity-feature-module-for-e-commerce-platform",
            "environment_setup": "Dockerfile",
            "FAIL_TO_PASS": [
                "TestPurchaseBehavior::test_purchase_frequency_empty",
                "TestPurchaseBehavior::test_purchase_frequency_single_purchase",
                "TestPurchaseBehavior::test_purchase_frequency_multiple_purchases",
                "TestPurchaseBehavior::test_average_order_value_empty",
                "TestPurchaseBehavior::test_average_order_value_single",
                "TestPurchaseBehavior::test_average_order_value_multiple",
                "TestPurchaseBehavior::test_average_order_value_with_time_filter",
                "TestPurchaseBehavior::test_purchase_recency_no_purchases",
                "TestPurchaseBehavior::test_purchase_recency_recent",
                "TestPurchaseBehavior::test_total_purchase_value",
                "TestPurchaseBehavior::test_purchase_invalid_data",
                "TestSessionEngagement::test_session_frequency_empty",
                "TestSessionEngagement::test_session_frequency_multiple",
                "TestSessionEngagement::test_average_session_duration_empty",
                "TestSessionEngagement::test_average_session_duration",
                "TestSessionEngagement::test_session_days_filtering",
                "TestSessionEngagement::test_device_usage_pattern",
                "TestSessionEngagement::test_primary_device",
                "TestSessionEngagement::test_primary_device_no_sessions",
                "TestSessionEngagement::test_session_invalid_data",
                "TestCartBehavior::test_abandoned_cart_count_empty",
                "TestCartBehavior::test_abandoned_cart_count",
                "TestCartBehavior::test_cart_conversion_ratio_empty",
                "TestCartBehavior::test_cart_conversion_ratio_all_converted",
                "TestCartBehavior::test_cart_conversion_ratio_mixed",
                "TestCartBehavior::test_abandoned_cart_value",
                "TestCartBehavior::test_cart_days_filtering",
                "TestCartBehavior::test_cart_invalid_data",
                "TestSupportInteractions::test_support_ticket_count_empty",
                "TestSupportInteractions::test_support_ticket_count",
                "TestSupportInteractions::test_average_response_time_empty",
                "TestSupportInteractions::test_average_response_time_no_times",
                "TestSupportInteractions::test_average_response_time",
                "TestSupportInteractions::test_escalation_count",
                "TestSupportInteractions::test_escalation_ratio",
                "TestSupportInteractions::test_escalation_ratio_empty",
                "TestSupportInteractions::test_support_days_filtering",
                "TestTradeoffIndicators::test_activity_retention_tradeoff_empty",
                "TestTradeoffIndicators::test_activity_retention_tradeoff_active_customer",
                "TestTradeoffIndicators::test_activity_retention_tradeoff_declining_engagement",
                "TestTradeoffIndicators::test_activity_retention_tradeoff_high_support_risk",
                "TestTradeoffIndicators::test_activity_retention_tradeoff_cart_abandonment",
                "TestTradeoffIndicators::test_retention_concern_true_for_long_recency",
                "TestTradeoffIndicators::test_activity_trend_values",
                "TestFeatureSummary::test_get_all_features_empty",
                "TestFeatureSummary::test_get_all_features_comprehensive",
                "TestFeatureSummary::test_get_feature_summary",
                "TestFeatureSummary::test_get_all_features_days_parameter_effect",
                "TestCohortFeatures::test_get_cohort_features_empty",
                "TestCohortFeatures::test_get_cohort_features_and_summary",
                "TestConvenienceFunctions::test_calculate_purchase_features",
                "TestConvenienceFunctions::test_calculate_purchase_features_empty",
                "TestConvenienceFunctions::test_calculate_session_features",
                "TestConvenienceFunctions::test_calculate_purchase_features_malformed",
                "TestConvenienceFunctions::test_calculate_session_features_malformed",
                "TestEdgeCases::test_none_customer_id",
                "TestEdgeCases::test_empty_string_customer_id",
                "TestEdgeCases::test_invalid_days_parameter",
                "TestEdgeCases::test_missing_data_fields",
                "TestEdgeCases::test_metadata_handling",
                "TestEdgeCases::test_unusual_metadata_sanitization",
                "TestEdgeCases::test_time_filtering_edge_cases",
                "TestScalability::test_multiple_customers",
                "TestScalability::test_large_purchase_history",
                "TestScalability::test_large_cart_history",
                "TestScalability::test_large_support_history",
                "TestScalability::test_no_hardcoded_customer_data"
            ],
            "PASS_TO_PASS": []
        }
        